srvp_fd/__init__.py
srvp_fd/frechet_distance.py
srvp_fd/py.typed
srvp_fd/srvp_model.py
srvp_fd-0.4.1.dist-info/WHEEL
srvp_fd-0.4.1.dist-info/METADATA
srvp_fd-0.4.1.dist-info/RECORD
