Metadata-Version: 2.3
Name: srvp-fd
Version: 0.4.1
Summary: Fréchet distance calculator for video datasets using SRVP encoder
Author: Naoki Kiyohara
Author-email: Naoki Kiyohara <n.kiyohara23@imperial.ac.uk>
License: Apache-2.0
Classifier: Programming Language :: Python :: 3
Classifier: Programming Language :: Python :: 3.8
Classifier: Programming Language :: Python :: 3.9
Classifier: Programming Language :: Python :: 3.10
Classifier: Programming Language :: Python :: 3.11
Classifier: Programming Language :: Python :: 3.12
Classifier: Programming Language :: Python :: 3.13
Classifier: License :: OSI Approved :: Apache Software License
Classifier: Operating System :: OS Independent
Classifier: Topic :: Scientific/Engineering :: Artificial Intelligence
Classifier: Topic :: Scientific/Engineering :: Image Processing
Requires-Dist: torch>=1.7.0
Requires-Dist: numpy>=1.19.0
Requires-Dist: scipy>=1.6.0
Requires-Dist: huggingface-hub>=0.16.0
Requires-Python: >=3.8
Project-URL: Bug Tracker, https://github.com/nkiyohara/srvp-fd/issues
Project-URL: Documentation, https://github.com/nkiyohara/srvp-fd#readme
Project-URL: Homepage, https://github.com/nkiyohara/srvp-fd
Project-URL: Source Code, https://github.com/nkiyohara/srvp-fd
